adafruit_motorkit.py
adafruit_circuitpython_motorkit-1.6.17.dist-info/licenses/LICENSE
adafruit_circuitpython_motorkit-1.6.17.dist-info/METADATA
adafruit_circuitpython_motorkit-1.6.17.dist-info/WHEEL
adafruit_circuitpython_motorkit-1.6.17.dist-info/top_level.txt
adafruit_circuitpython_motorkit-1.6.17.dist-info/RECORD
