Metadata-Version: 2.4
Name: adafruit-circuitpython-motorkit
Version: 1.6.17
Summary: CircuitPython helper library for DC & Stepper Motor FeatherWing, Shield, and Pi Hat kits.
Author-email: Adafruit Industries <circuitpython@adafruit.com>
License: MIT
Project-URL: Homepage, https://github.com/adafruit/Adafruit_CircuitPython_MotorKit
Keywords: adafruit,motor,pca9685,featherwing,pi,shield,motorkit,kit,i2c,hardware,micropython,circuitpython
Classifier: Intended Audience :: Developers
Classifier: Topic :: Software Development :: Libraries
Classifier: Topic :: Software Development :: Embedded Systems
Classifier: Topic :: System :: Hardware
Classifier: License :: OSI Approved :: MIT License
Classifier: Programming Language :: Python :: 3
License-File: LICENSE
Requires-Dist: Adafruit-Blinka
Requires-Dist: adafruit-circuitpython-busdevice
Requires-Dist: adafruit-circuitpython-pca9685
Requires-Dist: adafruit-circuitpython-motor
Requires-Dist: adafruit-circuitpython-register
Provides-Extra: optional
Dynamic: license-file
